[{"total_cpu_time (seconds)": 10.565719145, "total_cpu_memory (MB)": 35728.899836, "execution_time (seconds/batch)": 2.1164507833489825, "num_batches": 5, "batch_size": 512, "device": "cpu", "throughput_bps": 39712674.0018036, "sample_persec": 241.91443714548976, "result_path": "result-partition-50MB/4GB/3", "data_path": "50MB/1.pt"}, {"total_cpu_time (seconds)": 10.981764270000047, "total_cpu_memory (MB)": 35728.899844, "execution_time (seconds/batch)": 2.1997900259155023, "num_batches": 5, "batch_size": 512, "device": "cpu", "throughput_bps": 38208155.78296857, "sample_persec": 232.74948698202107, "result_path": "result-partition-50MB/4GB/3", "data_path": "50MB/10.pt"}, {"total_cpu_time (seconds)": 9.963504477999983, "total_cpu_memory (MB)": 35728.899836, "execution_time (seconds/batch)": 1.9958193633552392, "num_batches": 5, "batch_size": 512, "device": "cpu", "throughput_bps": 42112989.55367426, "sample_persec": 256.5362424078598, "result_path": "result-partition-50MB/4GB/3", "data_path": "50MB/108.pt"}, {"total_cpu_time (seconds)": 10.666519776000056, "total_cpu_memory (MB)": 35728.899804, "execution_time (seconds/batch)": 2.136642459042265, "num_batches": 5, "batch_size": 512, "device": "cpu", "throughput_bps": 39337381.71508339, "sample_persec": 239.62829992131694, "result_path": "result-partition-50MB/4GB/3", "data_path": "50MB/109.pt"}, {"total_cpu_time (seconds)": 10.345611258, "total_cpu_memory (MB)": 35728.899836, "execution_time (seconds/batch)": 2.0723603145915495, "num_batches": 5, "batch_size": 512, "device": "cpu", "throughput_bps": 40557580.36293306, "sample_persec": 247.0612838872628, "result_path": "result-partition-50MB/4GB/3", "data_path": "50MB/11.pt"}, {"total_cpu_time (seconds)": 10.875505059999945, "total_cpu_memory (MB)": 35728.899836, "execution_time (seconds/batch)": 2.178504925946781, "num_batches": 5, "batch_size": 512, "device": "cpu", "throughput_bps": 38581468.87754766, "sample_persec": 235.02356772385272, "result_path": "result-partition-50MB/4GB/3", "data_path": "50MB/110.pt"}, {"total_cpu_time (seconds)": 10.336967976999995, "total_cpu_memory (MB)": 35728.899836, "execution_time (seconds/batch)": 2.070628953139279, "num_batches": 5, "batch_size": 512, "device": "cpu", "throughput_bps": 40591492.682729065, "sample_persec": 247.2678647827063, "result_path": "result-partition-50MB/4GB/3", "data_path": "50MB/111.pt"}, {"total_cpu_time (seconds)": 9.71992449000001, "total_cpu_memory (MB)": 35728.899828, "execution_time (seconds/batch)": 1.947027127887326, "num_batches": 5, "batch_size": 512, "device": "cpu", "throughput_bps": 43168335.35401257, "sample_persec": 262.96500581148007, "result_path": "result-partition-50MB/4GB/3", "data_path": "50MB/112.pt"}, {"total_cpu_time (seconds)": 10.258698152999987, "total_cpu_memory (MB)": 35728.899844, "execution_time (seconds/batch)": 2.0549504907417813, "num_batches": 5, "batch_size": 512, "device": "cpu", "throughput_bps": 40901189.7749713, "sample_persec": 249.154421143831, "result_path": "result-partition-50MB/4GB/3", "data_path": "50MB/113.pt"}, {"total_cpu_time (seconds)": 11.102717079999978, "total_cpu_memory (MB)": 35728.899836, "execution_time (seconds/batch)": 2.224018444820027, "num_batches": 5, "batch_size": 512, "device": "cpu", "throughput_bps": 37791916.787273556, "sample_persec": 230.21391805113032, "result_path": "result-partition-50MB/4GB/3", "data_path": "50MB/114.pt"}, {"total_cpu_time (seconds)": 10.071811403999968, "total_cpu_memory (MB)": 35728.899836, "execution_time (seconds/batch)": 2.0175146474366135, "num_batches": 5, "batch_size": 512, "device": "cpu", "throughput_bps": 41660128.76624763, "sample_persec": 253.7775875136917, "result_path": "result-partition-50MB/4GB/3", "data_path": "50MB/115.pt"}, {"total_cpu_time (seconds)": 10.24747592199998, "total_cpu_memory (MB)": 35728.899836, "execution_time (seconds/batch)": 2.0527025321064123, "num_batches": 5, "batch_size": 512, "device": "cpu", "throughput_bps": 40945981.54645958, "sample_persec": 249.42727550231223, "result_path": "result-partition-50MB/4GB/3", "data_path": "50MB/116.pt"}, {"total_cpu_time (seconds)": 10.714806032000004, "total_cpu_memory (MB)": 35728.899836, "execution_time (seconds/batch)": 2.1463148233114246, "num_batches": 5, "batch_size": 512, "device": "cpu", "throughput_bps": 39160107.868203714, "sample_persec": 238.54841537648463, "result_path": "result-partition-50MB/4GB/3", "data_path": "50MB/100.pt"}, {"total_cpu_time (seconds)": 9.810128202999952, "total_cpu_memory (MB)": 35728.899836, "execution_time (seconds/batch)": 1.965096103261336, "num_batches": 5, "batch_size": 512, "device": "cpu", "throughput_bps": 42771404.340229504, "sample_persec": 260.54705372946825, "result_path": "result-partition-50MB/4GB/3", "data_path": "50MB/117.pt"}, {"total_cpu_time (seconds)": 10.900950470999993, "total_cpu_memory (MB)": 35728.899836, "execution_time (seconds/batch)": 2.183601972281689, "num_batches": 5, "batch_size": 512, "device": "cpu", "throughput_bps": 38491410.55325875, "sample_persec": 234.4749668205333, "result_path": "result-partition-50MB/4GB/3", "data_path": "50MB/118.pt"}, {"total_cpu_time (seconds)": 9.880983738000058, "total_cpu_memory (MB)": 35728.899844, "execution_time (seconds/batch)": 1.9792893872676172, "num_batches": 5, "batch_size": 512, "device": "cpu", "throughput_bps": 42464694.925702505, "sample_persec": 258.6786971594938, "result_path": "result-partition-50MB/4GB/3", "data_path": "50MB/119.pt"}, {"total_cpu_time (seconds)": 10.293027161000056, "total_cpu_memory (MB)": 35728.899836, "execution_time (seconds/batch)": 2.061827036945238, "num_batches": 5, "batch_size": 512, "device": "cpu", "throughput_bps": 40764777.30378717, "sample_persec": 248.3234484879823, "result_path": "result-partition-50MB/4GB/3", "data_path": "50MB/12.pt"}, {"total_cpu_time (seconds)": 9.90444442399999, "total_cpu_memory (MB)": 35728.899836, "execution_time (seconds/batch)": 1.983988867405319, "num_batches": 5, "batch_size": 512, "device": "cpu", "throughput_bps": 42364108.68067085, "sample_persec": 258.0659641853731, "result_path": "result-partition-50MB/4GB/3", "data_path": "50MB/120.pt"}, {"total_cpu_time (seconds)": 11.030243076000048, "total_cpu_memory (MB)": 35728.899836, "execution_time (seconds/batch)": 2.209500960450714, "num_batches": 5, "batch_size": 512, "device": "cpu", "throughput_bps": 38040227.8634243, "sample_persec": 231.72653425575234, "result_path": "result-partition-50MB/4GB/3", "data_path": "50MB/121.pt"}, {"total_cpu_time (seconds)": 10.027302972999998, "total_cpu_memory (MB)": 35728.899812, "execution_time (seconds/batch)": 2.008599030585289, "num_batches": 5, "batch_size": 512, "device": "cpu", "throughput_bps": 41845046.58229799, "sample_persec": 254.90403619820898, "result_path": "result-partition-50MB/4GB/3", "data_path": "50MB/122.pt"}, {"total_cpu_time (seconds)": 10.278847522000044, "total_cpu_memory (MB)": 35728.899844, "execution_time (seconds/batch)": 2.058986671073561, "num_batches": 5, "batch_size": 512, "device": "cpu", "throughput_bps": 40821012.190514155, "sample_persec": 248.66600993246925, "result_path": "result-partition-50MB/4GB/3", "data_path": "50MB/123.pt"}, {"total_cpu_time (seconds)": 10.99388724800005, "total_cpu_memory (MB)": 35728.899836, "execution_time (seconds/batch)": 2.2022184158748144, "num_batches": 5, "batch_size": 512, "device": "cpu", "throughput_bps": 38166023.58518186, "sample_persec": 232.4928337303963, "result_path": "result-partition-50MB/4GB/3", "data_path": "50MB/124.pt"}, {"total_cpu_time (seconds)": 10.435837020000013, "total_cpu_memory (MB)": 35728.899836, "execution_time (seconds/batch)": 2.090433706666669, "num_batches": 5, "batch_size": 512, "device": "cpu", "throughput_bps": 40206929.18027187, "sample_persec": 244.92525085448264, "result_path": "result-partition-50MB/4GB/3", "data_path": "50MB/125.pt"}, {"total_cpu_time (seconds)": 10.124995966999995, "total_cpu_memory (MB)": 35728.899836, "execution_time (seconds/batch)": 2.028168206222221, "num_batches": 5, "batch_size": 512, "device": "cpu", "throughput_bps": 41441296.506938174, "sample_persec": 252.44454499840506, "result_path": "result-partition-50MB/4GB/3", "data_path": "50MB/101.pt"}, {"total_cpu_time (seconds)": 13.824044282999994, "total_cpu_memory (MB)": 35728.899836, "execution_time (seconds/batch)": 2.769135631023473, "num_batches": 5, "batch_size": 512, "device": "cpu", "throughput_bps": 30352402.770872995, "sample_persec": 184.89524105063958, "result_path": "result-partition-50MB/4GB/3", "data_path": "50MB/126.pt"}, {"total_cpu_time (seconds)": 10.811183511000051, "total_cpu_memory (MB)": 35728.899836, "execution_time (seconds/batch)": 2.165620484206583, "num_batches": 5, "batch_size": 512, "device": "cpu", "throughput_bps": 38811010.799426064, "sample_persec": 236.4218494117085, "result_path": "result-partition-50MB/4GB/3", "data_path": "50MB/127.pt"}, {"total_cpu_time (seconds)": 15.368377052999959, "total_cpu_memory (MB)": 35728.899836, "execution_time (seconds/batch)": 3.0784855442629024, "num_batches": 5, "batch_size": 512, "device": "cpu", "throughput_bps": 27302359.810211323, "sample_persec": 166.31554465284674, "result_path": "result-partition-50MB/4GB/3", "data_path": "50MB/128.pt"}, {"total_cpu_time (seconds)": 9.73490877599999, "total_cpu_memory (MB)": 35728.899844, "execution_time (seconds/batch)": 1.950028675004693, "num_batches": 5, "batch_size": 512, "device": "cpu", "throughput_bps": 43101889.25801192, "sample_persec": 262.56024158145664, "result_path": "result-partition-50MB/4GB/3", "data_path": "50MB/129.pt"}, {"total_cpu_time (seconds)": 10.406785976000005, "total_cpu_memory (MB)": 35728.899836, "execution_time (seconds/batch)": 2.084614405208139, "num_batches": 5, "batch_size": 512, "device": "cpu", "throughput_bps": 40319168.75850621, "sample_persec": 245.60897148212848, "result_path": "result-partition-50MB/4GB/3", "data_path": "50MB/13.pt"}, {"total_cpu_time (seconds)": 10.547193113000088, "total_cpu_memory (MB)": 35728.899844, "execution_time (seconds/batch)": 2.1127397785039297, "num_batches": 5, "batch_size": 512, "device": "cpu", "throughput_bps": 39782428.88933407, "sample_persec": 242.3393572693352, "result_path": "result-partition-50MB/4GB/3", "data_path": "50MB/130.pt"}, {"total_cpu_time (seconds)": 14.975719165999994, "total_cpu_memory (MB)": 35728.899836, "execution_time (seconds/batch)": 2.9998310692456953, "num_batches": 5, "batch_size": 512, "device": "cpu", "throughput_bps": 28018217.712884173, "sample_persec": 170.67627749076615, "result_path": "result-partition-50MB/4GB/3", "data_path": "50MB/131.pt"}, {"total_cpu_time (seconds)": 10.416314743999992, "total_cpu_memory (MB)": 35728.899836, "execution_time (seconds/batch)": 2.086523141208136, "num_batches": 5, "batch_size": 512, "device": "cpu", "throughput_bps": 40282285.07992177, "sample_persec": 245.3842902042018, "result_path": "result-partition-50MB/4GB/3", "data_path": "50MB/132.pt"}, {"total_cpu_time (seconds)": 10.38369475799998, "total_cpu_memory (MB)": 35728.899836, "execution_time (seconds/batch)": 2.079988934309855, "num_batches": 5, "batch_size": 512, "device": "cpu", "throughput_bps": 40408830.36134418, "sample_persec": 246.15515570994262, "result_path": "result-partition-50MB/4GB/3", "data_path": "50MB/133.pt"}, {"total_cpu_time (seconds)": 10.852514229000015, "total_cpu_memory (MB)": 35728.899836, "execution_time (seconds/batch)": 2.1738995638685474, "num_batches": 5, "batch_size": 512, "device": "cpu", "throughput_bps": 38663202.93584749, "sample_persec": 235.52146037918791, "result_path": "result-partition-50MB/4GB/3", "data_path": "50MB/134.pt"}, {"total_cpu_time (seconds)": 12.003764728000018, "total_cpu_memory (MB)": 35728.899836, "execution_time (seconds/batch)": 2.404509992463227, "num_batches": 5, "batch_size": 512, "device": "cpu", "throughput_bps": 34955113.625415884, "sample_persec": 212.93319703591547, "result_path": "result-partition-50MB/4GB/3", "data_path": "50MB/102.pt"}, {"total_cpu_time (seconds)": 11.298819116000058, "total_cpu_memory (MB)": 35728.899836, "execution_time (seconds/batch)": 2.2633002298090883, "num_batches": 5, "batch_size": 512, "device": "cpu", "throughput_bps": 37136001.177841835, "sample_persec": 226.2183307617071, "result_path": "result-partition-50MB/4GB/3", "data_path": "50MB/135.pt"}, {"total_cpu_time (seconds)": 9.730968116000017, "total_cpu_memory (MB)": 35728.89982, "execution_time (seconds/batch)": 1.9492393096212868, "num_batches": 5, "batch_size": 512, "device": "cpu", "throughput_bps": 43119343.830763325, "sample_persec": 262.6665681698546, "result_path": "result-partition-50MB/4GB/3", "data_path": "50MB/136.pt"}, {"total_cpu_time (seconds)": 10.08309468599998, "total_cpu_memory (MB)": 35728.899836, "execution_time (seconds/batch)": 2.019774835380278, "num_batches": 5, "batch_size": 512, "device": "cpu", "throughput_bps": 41613509.84659402, "sample_persec": 253.49360286667897, "result_path": "result-partition-50MB/4GB/3", "data_path": "50MB/137.pt"}, {"total_cpu_time (seconds)": 10.323518713000032, "total_cpu_memory (MB)": 35728.899836, "execution_time (seconds/batch)": 2.067934890866986, "num_batches": 5, "batch_size": 512, "device": "cpu", "throughput_bps": 40644374.42939119, "sample_persec": 247.59000017903992, "result_path": "result-partition-50MB/4GB/3", "data_path": "50MB/138.pt"}, {"total_cpu_time (seconds)": 41.985231028999976, "total_cpu_memory (MB)": 35728.899828, "execution_time (seconds/batch)": 8.410187123179965, "num_batches": 5, "batch_size": 512, "device": "cpu", "throughput_bps": 9993822.820938615, "sample_persec": 60.878550322481814, "result_path": "result-partition-50MB/4GB/3", "data_path": "50MB/139.pt"}, {"total_cpu_time (seconds)": 10.904053578999978, "total_cpu_memory (MB)": 35728.899836, "execution_time (seconds/batch)": 2.1842235651204964, "num_batches": 5, "batch_size": 512, "device": "cpu", "throughput_bps": 38480456.55315656, "sample_persec": 234.40823923706483, "result_path": "result-partition-50MB/4GB/3", "data_path": "50MB/14.pt"}, {"total_cpu_time (seconds)": 10.270040777999991, "total_cpu_memory (MB)": 35728.899836, "execution_time (seconds/batch)": 2.057222565859153, "num_batches": 5, "batch_size": 512, "device": "cpu", "throughput_bps": 40856016.93995536, "sample_persec": 248.87924549193082, "result_path": "result-partition-50MB/4GB/3", "data_path": "50MB/140.pt"}, {"total_cpu_time (seconds)": 9.929320849000014, "total_cpu_memory (MB)": 35728.899836, "execution_time (seconds/batch)": 1.988971938453837, "num_batches": 5, "batch_size": 512, "device": "cpu", "throughput_bps": 42257971.75667431, "sample_persec": 257.4194185957256, "result_path": "result-partition-50MB/4GB/3", "data_path": "50MB/141.pt"}, {"total_cpu_time (seconds)": 15.224053404000035, "total_cpu_memory (MB)": 35728.899836, "execution_time (seconds/batch)": 3.049575642741791, "num_batches": 5, "batch_size": 512, "device": "cpu", "throughput_bps": 27561185.504627455, "sample_persec": 167.89221189466042, "result_path": "result-partition-50MB/4GB/3", "data_path": "50MB/142.pt"}, {"total_cpu_time (seconds)": 10.502770231, "total_cpu_memory (MB)": 35728.899836, "execution_time (seconds/batch)": 2.103841298228482, "num_batches": 5, "batch_size": 512, "device": "cpu", "throughput_bps": 39950694.03323025, "sample_persec": 243.3643642375137, "result_path": "result-partition-50MB/4GB/3", "data_path": "50MB/143.pt"}, {"total_cpu_time (seconds)": 10.737950518999972, "total_cpu_memory (MB)": 35728.899836, "execution_time (seconds/batch)": 2.1509509646823104, "num_batches": 5, "batch_size": 512, "device": "cpu", "throughput_bps": 39075702.50557243, "sample_persec": 238.0342501557775, "result_path": "result-partition-50MB/4GB/3", "data_path": "50MB/103.pt"}, {"total_cpu_time (seconds)": 11.042329076000051, "total_cpu_memory (MB)": 35728.899836, "execution_time (seconds/batch)": 2.211921943236317, "num_batches": 5, "batch_size": 512, "device": "cpu", "throughput_bps": 37998592.24554032, "sample_persec": 231.47290597916864, "result_path": "result-partition-50MB/4GB/3", "data_path": "50MB/144.pt"}, {"total_cpu_time (seconds)": 10.648424237000002, "total_cpu_memory (MB)": 35728.899836, "execution_time (seconds/batch)": 2.1330176875367766, "num_batches": 5, "batch_size": 512, "device": "cpu", "throughput_bps": 39404230.20920254, "sample_persec": 240.03551540693556, "result_path": "result-partition-50MB/4GB/3", "data_path": "50MB/145.pt"}, {"total_cpu_time (seconds)": 10.826320218000038, "total_cpu_memory (MB)": 35728.899836, "execution_time (seconds/batch)": 2.168652563230055, "num_batches": 5, "batch_size": 512, "device": "cpu", "throughput_bps": 38756747.588379756, "sample_persec": 236.09129866215739, "result_path": "result-partition-50MB/4GB/3", "data_path": "50MB/146.pt"}, {"total_cpu_time (seconds)": 10.129747684999986, "total_cpu_memory (MB)": 35728.899836, "execution_time (seconds/batch)": 2.0291200370579, "num_batches": 5, "batch_size": 512, "device": "cpu", "throughput_bps": 41421856.99465431, "sample_persec": 252.32612691675385, "result_path": "result-partition-50MB/4GB/3", "data_path": "50MB/147.pt"}, {"total_cpu_time (seconds)": 10.882717857, "total_cpu_memory (MB)": 35728.899836, "execution_time (seconds/batch)": 2.1799497428732395, "num_batches": 5, "batch_size": 512, "device": "cpu", "throughput_bps": 38555898.031493, "sample_persec": 234.86779989944566, "result_path": "result-partition-50MB/4GB/3", "data_path": "50MB/148.pt"}, {"total_cpu_time (seconds)": 9.885084911000042, "total_cpu_memory (MB)": 35728.899852, "execution_time (seconds/batch)": 1.9801109054898363, "num_batches": 5, "batch_size": 512, "device": "cpu", "throughput_bps": 42447076.96269562, "sample_persec": 258.5713752600854, "result_path": "result-partition-50MB/4GB/3", "data_path": "50MB/149.pt"}, {"total_cpu_time (seconds)": 10.083738961999954, "total_cpu_memory (MB)": 35728.899836, "execution_time (seconds/batch)": 2.0199038922316026, "num_batches": 5, "batch_size": 512, "device": "cpu", "throughput_bps": 41610851.052492954, "sample_persec": 253.47740650885086, "result_path": "result-partition-50MB/4GB/3", "data_path": "50MB/15.pt"}, {"total_cpu_time (seconds)": 10.75706794399998, "total_cpu_memory (MB)": 35728.899836, "execution_time (seconds/batch)": 2.154780433226913, "num_batches": 5, "batch_size": 512, "device": "cpu", "throughput_bps": 39006257.29839685, "sample_persec": 237.6112164863356, "result_path": "result-partition-50MB/4GB/3", "data_path": "50MB/150.pt"}, {"total_cpu_time (seconds)": 10.494893738999973, "total_cpu_memory (MB)": 35728.899836, "execution_time (seconds/batch)": 2.1022635345727645, "num_batches": 5, "batch_size": 512, "device": "cpu", "throughput_bps": 39980677.31174396, "sample_persec": 243.54701091461965, "result_path": "result-partition-50MB/4GB/3", "data_path": "50MB/151.pt"}, {"total_cpu_time (seconds)": 10.254371005999985, "total_cpu_memory (MB)": 35728.899836, "execution_time (seconds/batch)": 2.0540837069921722, "num_batches": 5, "batch_size": 512, "device": "cpu", "throughput_bps": 40918449.289038785, "sample_persec": 249.25955950925183, "result_path": "result-partition-50MB/4GB/3", "data_path": "50MB/152.pt"}, {"total_cpu_time (seconds)": 10.809447586999978, "total_cpu_memory (MB)": 35728.899836, "execution_time (seconds/batch)": 2.165272756081373, "num_batches": 5, "batch_size": 512, "device": "cpu", "throughput_bps": 38817243.584642105, "sample_persec": 236.45981715790757, "result_path": "result-partition-50MB/4GB/3", "data_path": "50MB/104.pt"}, {"total_cpu_time (seconds)": 10.66605744999998, "total_cpu_memory (MB)": 35728.899836, "execution_time (seconds/batch)": 2.1365498491392763, "num_batches": 5, "batch_size": 512, "device": "cpu", "throughput_bps": 39339086.81506312, "sample_persec": 239.63868673893225, "result_path": "result-partition-50MB/4GB/3", "data_path": "50MB/153.pt"}, {"total_cpu_time (seconds)": 10.147830052000023, "total_cpu_memory (MB)": 35728.899844, "execution_time (seconds/batch)": 2.0327421700406934, "num_batches": 5, "batch_size": 512, "device": "cpu", "throughput_bps": 41348047.59735831, "sample_persec": 251.87650826850822, "result_path": "result-partition-50MB/4GB/3", "data_path": "50MB/154.pt"}, {"total_cpu_time (seconds)": 10.201803000000028, "total_cpu_memory (MB)": 35728.899836, "execution_time (seconds/batch)": 2.0435536525821654, "num_batches": 5, "batch_size": 512, "device": "cpu", "throughput_bps": 41129294.49823711, "sample_persec": 250.543947966844, "result_path": "result-partition-50MB/4GB/3", "data_path": "50MB/155.pt"}, {"total_cpu_time (seconds)": 10.109005212000012, "total_cpu_memory (MB)": 35728.899836, "execution_time (seconds/batch)": 2.0249650502910823, "num_batches": 5, "batch_size": 512, "device": "cpu", "throughput_bps": 41506849.70484705, "sample_persec": 252.84387003439969, "result_path": "result-partition-50MB/4GB/3", "data_path": "50MB/156.pt"}, {"total_cpu_time (seconds)": 10.01807000400005, "total_cpu_memory (MB)": 35728.899836, "execution_time (seconds/batch)": 2.0067495469671464, "num_batches": 5, "batch_size": 512, "device": "cpu", "throughput_bps": 41883612.29582778, "sample_persec": 255.13896379037394, "result_path": "result-partition-50MB/4GB/3", "data_path": "50MB/157.pt"}, {"total_cpu_time (seconds)": 10.938640218000032, "total_cpu_memory (MB)": 35728.899844, "execution_time (seconds/batch)": 2.191151718159631, "num_batches": 5, "batch_size": 512, "device": "cpu", "throughput_bps": 38358786.06826657, "sample_persec": 233.66706912930414, "result_path": "result-partition-50MB/4GB/3", "data_path": "50MB/158.pt"}, {"total_cpu_time (seconds)": 11.168867692000042, "total_cpu_memory (MB)": 35728.899836, "execution_time (seconds/batch)": 2.237269271636941, "num_batches": 5, "batch_size": 512, "device": "cpu", "throughput_bps": 37568084.03241656, "sample_persec": 228.8504144274888, "result_path": "result-partition-50MB/4GB/3", "data_path": "50MB/159.pt"}, {"total_cpu_time (seconds)": 10.028071668000063, "total_cpu_memory (MB)": 35728.899836, "execution_time (seconds/batch)": 2.0087530101784163, "num_batches": 5, "batch_size": 512, "device": "cpu", "throughput_bps": 41841838.978767596, "sample_persec": 254.88449670301898, "result_path": "result-partition-50MB/4GB/3", "data_path": "50MB/16.pt"}, {"total_cpu_time (seconds)": 10.093222796000019, "total_cpu_memory (MB)": 35728.899836, "execution_time (seconds/batch)": 2.021803627367766, "num_batches": 5, "batch_size": 512, "device": "cpu", "throughput_bps": 41571752.49973539, "sample_persec": 253.23923306369025, "result_path": "result-partition-50MB/4GB/3", "data_path": "50MB/160.pt"}, {"total_cpu_time (seconds)": 11.841739686000114, "total_cpu_memory (MB)": 35728.899836, "execution_time (seconds/batch)": 2.372054272000023, "num_batches": 5, "batch_size": 512, "device": "cpu", "throughput_bps": 35433388.26271138, "sample_persec": 215.8466633937097, "result_path": "result-partition-50MB/4GB/3", "data_path": "50MB/161.pt"}, {"total_cpu_time (seconds)": 14.391514426000018, "total_cpu_memory (MB)": 35728.899836, "execution_time (seconds/batch)": 2.882807271561819, "num_batches": 5, "batch_size": 512, "device": "cpu", "throughput_bps": 29155580.68315273, "sample_persec": 177.6046581576068, "result_path": "result-partition-50MB/4GB/3", "data_path": "50MB/105.pt"}, {"total_cpu_time (seconds)": 10.156507275999973, "total_cpu_memory (MB)": 35728.899836, "execution_time (seconds/batch)": 2.0344803307167396, "num_batches": 5, "batch_size": 512, "device": "cpu", "throughput_bps": 41312721.84400502, "sample_persec": 251.66131727585903, "result_path": "result-partition-50MB/4GB/3", "data_path": "50MB/162.pt"}, {"total_cpu_time (seconds)": 9.680975665999979, "total_cpu_memory (MB)": 35728.899836, "execution_time (seconds/batch)": 1.939225172532077, "num_batches": 5, "batch_size": 512, "device": "cpu", "throughput_bps": 43342011.63975955, "sample_persec": 264.0229753883988, "result_path": "result-partition-50MB/4GB/3", "data_path": "50MB/163.pt"}, {"total_cpu_time (seconds)": 10.754020167999998, "total_cpu_memory (MB)": 35728.899836, "execution_time (seconds/batch)": 2.154169924106416, "num_batches": 5, "batch_size": 512, "device": "cpu", "throughput_bps": 39017311.98613092, "sample_persec": 237.67855742038816, "result_path": "result-partition-50MB/4GB/3", "data_path": "50MB/164.pt"}, {"total_cpu_time (seconds)": 10.549187907000038, "total_cpu_memory (MB)": 35728.899836, "execution_time (seconds/batch)": 2.1131393616525895, "num_batches": 5, "batch_size": 512, "device": "cpu", "throughput_bps": 39774906.24861978, "sample_persec": 242.2935322162511, "result_path": "result-partition-50MB/4GB/3", "data_path": "50MB/165.pt"}, {"total_cpu_time (seconds)": 10.118681709000024, "total_cpu_memory (MB)": 35728.899844, "execution_time (seconds/batch)": 2.0269033783286434, "num_batches": 5, "batch_size": 512, "device": "cpu", "throughput_bps": 41467156.697575994, "sample_persec": 252.60207539946387, "result_path": "result-partition-50MB/4GB/3", "data_path": "50MB/166.pt"}, {"total_cpu_time (seconds)": 14.233183867999983, "total_cpu_memory (MB)": 35728.899836, "execution_time (seconds/batch)": 2.8510916042316086, "num_batches": 5, "batch_size": 512, "device": "cpu", "throughput_bps": 29479908.634030756, "sample_persec": 179.58034011958307, "result_path": "result-partition-50MB/4GB/3", "data_path": "50MB/167.pt"}, {"total_cpu_time (seconds)": 10.07937740200002, "total_cpu_memory (MB)": 35728.899836, "execution_time (seconds/batch)": 2.019030215111115, "num_batches": 5, "batch_size": 512, "device": "cpu", "throughput_bps": 41628856.94871803, "sample_persec": 253.58709154920825, "result_path": "result-partition-50MB/4GB/3", "data_path": "50MB/168.pt"}, {"total_cpu_time (seconds)": 9.553110000000006, "total_cpu_memory (MB)": 35728.899836, "execution_time (seconds/batch)": 1.9136120187793437, "num_batches": 5, "batch_size": 512, "device": "cpu", "throughput_bps": 43922132.16428993, "sample_persec": 267.55684797934896, "result_path": "result-partition-50MB/4GB/3", "data_path": "50MB/169.pt"}, {"total_cpu_time (seconds)": 10.013615719000024, "total_cpu_memory (MB)": 35728.899836, "execution_time (seconds/batch)": 2.0058572958247307, "num_batches": 5, "batch_size": 512, "device": "cpu", "throughput_bps": 41902243.08327075, "sample_persec": 255.25245542928087, "result_path": "result-partition-50MB/4GB/3", "data_path": "50MB/17.pt"}, {"total_cpu_time (seconds)": 10.960091140000008, "total_cpu_memory (MB)": 35728.899836, "execution_time (seconds/batch)": 2.1954486164632256, "num_batches": 5, "batch_size": 512, "device": "cpu", "throughput_bps": 38283710.84147752, "sample_persec": 233.20973953141763, "result_path": "result-partition-50MB/4GB/3", "data_path": "50MB/170.pt"}, {"total_cpu_time (seconds)": 10.936810250000017, "total_cpu_memory (MB)": 35728.899836, "execution_time (seconds/batch)": 2.19078515179969, "num_batches": 5, "batch_size": 512, "device": "cpu", "throughput_bps": 38365204.33368581, "sample_persec": 233.70616675003538, "result_path": "result-partition-50MB/4GB/3", "data_path": "50MB/106.pt"}, {"total_cpu_time (seconds)": 10.32133980099999, "total_cpu_memory (MB)": 35728.899836, "execution_time (seconds/batch)": 2.0674984264913907, "num_batches": 5, "batch_size": 512, "device": "cpu", "throughput_bps": 40652954.760713086, "sample_persec": 247.64226827919765, "result_path": "result-partition-50MB/4GB/3", "data_path": "50MB/171.pt"}, {"total_cpu_time (seconds)": 11.21333829299999, "total_cpu_memory (MB)": 35728.899836, "execution_time (seconds/batch)": 2.2461773106478855, "num_batches": 5, "batch_size": 512, "device": "cpu", "throughput_bps": 37419094.03214331, "sample_persec": 227.94282426987883, "result_path": "result-partition-50MB/4GB/3", "data_path": "50MB/172.pt"}, {"total_cpu_time (seconds)": 10.204157236999967, "total_cpu_memory (MB)": 35728.899836, "execution_time (seconds/batch)": 2.0440252368325442, "num_batches": 5, "batch_size": 512, "device": "cpu", "throughput_bps": 41119805.41406874, "sample_persec": 250.48614409154936, "result_path": "result-partition-50MB/4GB/3", "data_path": "50MB/107.pt"}]