[{"total_cpu_time (seconds)": 28.233450210999976, "total_cpu_memory (MB)": 71466.748204, "execution_time (seconds/batch)": 0.7068025869368271, "num_batches": 40, "batch_size": 128, "device": "cpu", "throughput_bps": 29728923.448150966, "sample_persec": 181.09724322704048, "result_path": "result/Batches/128/run 2", "data_path": "1.pt"}, {"total_cpu_time (seconds)": 26.253515999999685, "total_cpu_memory (MB)": 71466.75698, "execution_time (seconds/batch)": 0.6572364654801408, "num_batches": 40, "batch_size": 128, "device": "cpu", "throughput_bps": 31970958.86128205, "sample_persec": 194.7548663577123, "result_path": "result/Batches/128/run 2", "data_path": "10.pt"}, {"total_cpu_time (seconds)": 47.11780482500045, "total_cpu_memory (MB)": 71466.739564, "execution_time (seconds/batch)": 1.1795577973010087, "num_batches": 40, "batch_size": 128, "device": "cpu", "throughput_bps": 17813862.15078181, "sample_persec": 108.51524214657535, "result_path": "result/Batches/128/run 2", "data_path": "108.pt"}, {"total_cpu_time (seconds)": 23.337290811000308, "total_cpu_memory (MB)": 71466.74826, "execution_time (seconds/batch)": 0.5842310236276236, "num_batches": 40, "batch_size": 128, "device": "cpu", "throughput_bps": 35966046.221798904, "sample_persec": 219.09141216982766, "result_path": "result/Batches/128/run 2", "data_path": "109.pt"}, {"total_cpu_time (seconds)": 24.645608723000084, "total_cpu_memory (MB)": 71466.748276, "execution_time (seconds/batch)": 0.6169837505464524, "num_batches": 40, "batch_size": 128, "device": "cpu", "throughput_bps": 34056780.23349819, "sample_persec": 207.4608932352473, "result_path": "result/Batches/128/run 2", "data_path": "11.pt"}, {"total_cpu_time (seconds)": 24.05616635399992, "total_cpu_memory (MB)": 71466.748228, "execution_time (seconds/batch)": 0.6022275167830999, "num_batches": 40, "batch_size": 128, "device": "cpu", "throughput_bps": 34891265.20196506, "sample_persec": 212.54425683458246, "result_path": "result/Batches/128/run 2", "data_path": "110.pt"}, {"total_cpu_time (seconds)": 50.39308363999995, "total_cpu_memory (MB)": 71466.756972, "execution_time (seconds/batch)": 1.2615518689458232, "num_batches": 40, "batch_size": 128, "device": "cpu", "throughput_bps": 16656057.128715944, "sample_persec": 101.46233631040414, "result_path": "result/Batches/128/run 2", "data_path": "111.pt"}, {"total_cpu_time (seconds)": 22.652028758000025, "total_cpu_memory (MB)": 71466.75698, "execution_time (seconds/batch)": 0.5670760181936247, "num_batches": 40, "batch_size": 128, "device": "cpu", "throughput_bps": 37054079.74566368, "sample_persec": 225.71929669629438, "result_path": "result/Batches/128/run 2", "data_path": "112.pt"}, {"total_cpu_time (seconds)": 22.23499875099969, "total_cpu_memory (MB)": 71466.756972, "execution_time (seconds/batch)": 0.5566359945487894, "num_batches": 40, "batch_size": 128, "device": "cpu", "throughput_bps": 37749050.017925575, "sample_persec": 229.9527900702094, "result_path": "result/Batches/128/run 2", "data_path": "113.pt"}, {"total_cpu_time (seconds)": 22.29853963400034, "total_cpu_memory (MB)": 71466.756964, "execution_time (seconds/batch)": 0.5582266914046633, "num_batches": 40, "batch_size": 128, "device": "cpu", "throughput_bps": 37641482.07805397, "sample_persec": 229.29752727859392, "result_path": "result/Batches/128/run 2", "data_path": "114.pt"}, {"total_cpu_time (seconds)": 21.862434821000157, "total_cpu_memory (MB)": 71466.756972, "execution_time (seconds/batch)": 0.5473091447463369, "num_batches": 40, "batch_size": 128, "device": "cpu", "throughput_bps": 38392342.24697401, "sample_persec": 233.8714805493056, "result_path": "result/Batches/128/run 2", "data_path": "115.pt"}, {"total_cpu_time (seconds)": 22.20843550299974, "total_cpu_memory (MB)": 71466.756972, "execution_time (seconds/batch)": 0.555971004182274, "num_batches": 40, "batch_size": 128, "device": "cpu", "throughput_bps": 37794201.211815536, "sample_persec": 230.2278338926385, "result_path": "result/Batches/128/run 2", "data_path": "116.pt"}, {"total_cpu_time (seconds)": 24.89266661699968, "total_cpu_memory (MB)": 71466.75698, "execution_time (seconds/batch)": 0.623168653818885, "num_batches": 40, "batch_size": 128, "device": "cpu", "throughput_bps": 33718769.182679355, "sample_persec": 205.40185905628263, "result_path": "result/Batches/128/run 2", "data_path": "100.pt"}, {"total_cpu_time (seconds)": 21.76961419299959, "total_cpu_memory (MB)": 71466.75698, "execution_time (seconds/batch)": 0.5449854521228139, "num_batches": 40, "batch_size": 128, "device": "cpu", "throughput_bps": 38556038.36424019, "sample_persec": 234.86865475292515, "result_path": "result/Batches/128/run 2", "data_path": "117.pt"}, {"total_cpu_time (seconds)": 21.344830871000212, "total_cpu_memory (MB)": 71466.756996, "execution_time (seconds/batch)": 0.53435133023431, "num_batches": 40, "batch_size": 128, "device": "cpu", "throughput_bps": 39323341.799834475, "sample_persec": 239.54277412179871, "result_path": "result/Batches/128/run 2", "data_path": "118.pt"}, {"total_cpu_time (seconds)": 20.953734197000497, "total_cpu_memory (MB)": 71466.756876, "execution_time (seconds/batch)": 0.5245605275212328, "num_batches": 40, "batch_size": 128, "device": "cpu", "throughput_bps": 40057303.013806105, "sample_persec": 244.01378541548553, "result_path": "result/Batches/128/run 2", "data_path": "119.pt"}, {"total_cpu_time (seconds)": 20.419881166000046, "total_cpu_memory (MB)": 71466.74818, "execution_time (seconds/batch)": 0.5111959298353229, "num_batches": 40, "batch_size": 128, "device": "cpu", "throughput_bps": 41104552.62577888, "sample_persec": 250.3932299328636, "result_path": "result/Batches/128/run 2", "data_path": "12.pt"}, {"total_cpu_time (seconds)": 21.142180956999887, "total_cpu_memory (MB)": 71466.74822, "execution_time (seconds/batch)": 0.5292781463907658, "num_batches": 40, "batch_size": 128, "device": "cpu", "throughput_bps": 39700259.954595774, "sample_persec": 241.8388155128885, "result_path": "result/Batches/128/run 2", "data_path": "120.pt"}, {"total_cpu_time (seconds)": 21.377268681000132, "total_cpu_memory (MB)": 71466.756964, "execution_time (seconds/batch)": 0.5351633857164124, "num_batches": 40, "batch_size": 128, "device": "cpu", "throughput_bps": 39263672.66675207, "sample_persec": 239.17929256062422, "result_path": "result/Batches/128/run 2", "data_path": "121.pt"}, {"total_cpu_time (seconds)": 22.714178663000055, "total_cpu_memory (MB)": 71464.659764, "execution_time (seconds/batch)": 0.5686318929912003, "num_batches": 40, "batch_size": 128, "device": "cpu", "throughput_bps": 36952693.40146767, "sample_persec": 225.10168982375532, "result_path": "result/Batches/128/run 2", "data_path": "122.pt"}, {"total_cpu_time (seconds)": 22.26124409400008, "total_cpu_memory (MB)": 71466.756924, "execution_time (seconds/batch)": 0.5572930264095463, "num_batches": 40, "batch_size": 128, "device": "cpu", "throughput_bps": 37704545.013556734, "sample_persec": 229.68168258745573, "result_path": "result/Batches/128/run 2", "data_path": "123.pt"}, {"total_cpu_time (seconds)": 22.14546813799981, "total_cpu_memory (MB)": 71466.756932, "execution_time (seconds/batch)": 0.5543946649059213, "num_batches": 40, "batch_size": 128, "device": "cpu", "throughput_bps": 37901663.43603927, "sample_persec": 230.88245270491757, "result_path": "result/Batches/128/run 2", "data_path": "124.pt"}, {"total_cpu_time (seconds)": 52.69623541100011, "total_cpu_memory (MB)": 71466.756988, "execution_time (seconds/batch)": 1.3192094920023498, "num_batches": 40, "batch_size": 128, "device": "cpu", "throughput_bps": 15928084.30153607, "sample_persec": 97.02780398109205, "result_path": "result/Batches/128/run 2", "data_path": "125.pt"}, {"total_cpu_time (seconds)": 25.012360492000337, "total_cpu_memory (MB)": 71466.756716, "execution_time (seconds/batch)": 0.6261650973941019, "num_batches": 40, "batch_size": 128, "device": "cpu", "throughput_bps": 33557411.7552179, "sample_persec": 204.41893125741902, "result_path": "result/Batches/128/run 2", "data_path": "101.pt"}, {"total_cpu_time (seconds)": 24.36039709299986, "total_cpu_memory (MB)": 71466.459788, "execution_time (seconds/batch)": 0.6098436980058639, "num_batches": 40, "batch_size": 128, "device": "cpu", "throughput_bps": 34455517.15744377, "sample_persec": 209.88984623199175, "result_path": "result/Batches/128/run 2", "data_path": "126.pt"}, {"total_cpu_time (seconds)": 20.603666352000108, "total_cpu_memory (MB)": 71466.756924, "execution_time (seconds/batch)": 0.5157968498055963, "num_batches": 40, "batch_size": 128, "device": "cpu", "throughput_bps": 40737899.054481626, "sample_persec": 248.1597164624855, "result_path": "result/Batches/128/run 2", "data_path": "127.pt"}, {"total_cpu_time (seconds)": 20.99877790699999, "total_cpu_memory (MB)": 71466.74822, "execution_time (seconds/batch)": 0.525688161958928, "num_batches": 40, "batch_size": 128, "device": "cpu", "throughput_bps": 39971377.5590817, "sample_persec": 243.49036037452302, "result_path": "result/Batches/128/run 2", "data_path": "128.pt"}, {"total_cpu_time (seconds)": 23.27934392000003, "total_cpu_memory (MB)": 71466.75698, "execution_time (seconds/batch)": 0.5827803680344228, "num_batches": 40, "batch_size": 128, "device": "cpu", "throughput_bps": 36055572.82389249, "sample_persec": 219.63677402468622, "result_path": "result/Batches/128/run 2", "data_path": "129.pt"}, {"total_cpu_time (seconds)": 23.11891529399974, "total_cpu_memory (MB)": 71466.756948, "execution_time (seconds/batch)": 0.5787641614770129, "num_batches": 40, "batch_size": 128, "device": "cpu", "throughput_bps": 36305772.53846525, "sample_persec": 221.16089509299005, "result_path": "result/Batches/128/run 2", "data_path": "13.pt"}, {"total_cpu_time (seconds)": 1.7563352509999974, "total_cpu_memory (MB)": 3356.82764, "execution_time (seconds/batch)": 0.9367121338666653, "num_batches": 2, "batch_size": 128, "device": "cpu", "throughput_bps": 22432163.77828088, "sample_persec": 136.64817116399172, "result_path": "result/Batches/128/run 2", "data_path": "130.pt"}, {"total_cpu_time (seconds)": 22.677639294000194, "total_cpu_memory (MB)": 71466.75698, "execution_time (seconds/batch)": 0.5677171581521661, "num_batches": 40, "batch_size": 128, "device": "cpu", "throughput_bps": 37012233.46567939, "sample_persec": 225.46438514668247, "result_path": "result/Batches/128/run 2", "data_path": "14.pt"}, {"total_cpu_time (seconds)": 28.669776290000076, "total_cpu_memory (MB)": 71466.756972, "execution_time (seconds/batch)": 0.7177256728183082, "num_batches": 40, "batch_size": 128, "device": "cpu", "throughput_bps": 29276478.180709157, "sample_persec": 178.3411195218638, "result_path": "result/Batches/128/run 2", "data_path": "15.pt"}, {"total_cpu_time (seconds)": 54.177155666000004, "total_cpu_memory (MB)": 71466.7569, "execution_time (seconds/batch)": 1.356283185067084, "num_batches": 40, "batch_size": 128, "device": "cpu", "throughput_bps": 15492693.731921986, "sample_persec": 94.37557097905693, "result_path": "result/Batches/128/run 2", "data_path": "16.pt"}, {"total_cpu_time (seconds)": 23.329638055, "total_cpu_memory (MB)": 71466.756964, "execution_time (seconds/batch)": 0.5840394428007041, "num_batches": 40, "batch_size": 128, "device": "cpu", "throughput_bps": 35977844.06347062, "sample_persec": 219.1632801137343, "result_path": "result/Batches/128/run 2", "data_path": "17.pt"}, {"total_cpu_time (seconds)": 27.051308333000286, "total_cpu_memory (MB)": 71466.748092, "execution_time (seconds/batch)": 0.6772085794296961, "num_batches": 40, "batch_size": 128, "device": "cpu", "throughput_bps": 31028077.077368736, "sample_persec": 189.011190773445, "result_path": "result/Batches/128/run 2", "data_path": "102.pt"}, {"total_cpu_time (seconds)": 49.54132208299973, "total_cpu_memory (MB)": 71466.75698, "execution_time (seconds/batch)": 1.2402286772196294, "num_batches": 40, "batch_size": 128, "device": "cpu", "throughput_bps": 16942423.914198, "sample_persec": 103.2067733564693, "result_path": "result/Batches/128/run 2", "data_path": "18.pt"}, {"total_cpu_time (seconds)": 39.92776747899987, "total_cpu_memory (MB)": 71466.75698, "execution_time (seconds/batch)": 0.9995607739706597, "num_batches": 40, "batch_size": 128, "device": "cpu", "throughput_bps": 21021713.28365551, "sample_persec": 128.05624563630306, "result_path": "result/Batches/128/run 2", "data_path": "19.pt"}, {"total_cpu_time (seconds)": 49.354345695, "total_cpu_memory (MB)": 71466.748276, "execution_time (seconds/batch)": 1.2355478679757481, "num_batches": 40, "batch_size": 128, "device": "cpu", "throughput_bps": 17006609.411601074, "sample_persec": 103.59776688353482, "result_path": "result/Batches/128/run 2", "data_path": "2.pt"}, {"total_cpu_time (seconds)": 21.311381653999877, "total_cpu_memory (MB)": 71466.75694, "execution_time (seconds/batch)": 0.5335139549602942, "num_batches": 40, "batch_size": 128, "device": "cpu", "throughput_bps": 39385061.63641739, "sample_persec": 239.91874778519366, "result_path": "result/Batches/128/run 2", "data_path": "20.pt"}, {"total_cpu_time (seconds)": 29.218480704999724, "total_cpu_memory (MB)": 71466.756972, "execution_time (seconds/batch)": 0.731462063414818, "num_batches": 40, "batch_size": 128, "device": "cpu", "throughput_bps": 28726684.610140406, "sample_persec": 174.99198714754147, "result_path": "result/Batches/128/run 2", "data_path": "21.pt"}, {"total_cpu_time (seconds)": 22.564248440999755, "total_cpu_memory (MB)": 71466.7569, "execution_time (seconds/batch)": 0.5648785058572205, "num_batches": 40, "batch_size": 128, "device": "cpu", "throughput_bps": 37198228.96803785, "sample_persec": 226.5973986844411, "result_path": "result/Batches/128/run 2", "data_path": "22.pt"}, {"total_cpu_time (seconds)": 25.876581092000272, "total_cpu_memory (MB)": 71466.756948, "execution_time (seconds/batch)": 0.6478001916244934, "num_batches": 40, "batch_size": 128, "device": "cpu", "throughput_bps": 32436668.392003477, "sample_persec": 197.59179088696075, "result_path": "result/Batches/128/run 2", "data_path": "23.pt"}, {"total_cpu_time (seconds)": 22.14406080999973, "total_cpu_memory (MB)": 71466.748284, "execution_time (seconds/batch)": 0.5543594335380335, "num_batches": 40, "batch_size": 128, "device": "cpu", "throughput_bps": 37904072.21158685, "sample_persec": 230.8971260452415, "result_path": "result/Batches/128/run 2", "data_path": "24.pt"}, {"total_cpu_time (seconds)": 25.886156213000017, "total_cpu_memory (MB)": 71466.756964, "execution_time (seconds/batch)": 0.6480398973721889, "num_batches": 40, "batch_size": 128, "device": "cpu", "throughput_bps": 32424670.279107668, "sample_persec": 197.5187029672738, "result_path": "result/Batches/128/run 2", "data_path": "25.pt"}, {"total_cpu_time (seconds)": 22.62353463900008, "total_cpu_memory (MB)": 71466.748204, "execution_time (seconds/batch)": 0.5663626899651888, "num_batches": 40, "batch_size": 128, "device": "cpu", "throughput_bps": 37100748.9940616, "sample_persec": 226.0035879267885, "result_path": "result/Batches/128/run 2", "data_path": "26.pt"}, {"total_cpu_time (seconds)": 32.721003182000196, "total_cpu_memory (MB)": 71466.756964, "execution_time (seconds/batch)": 0.8191450043606542, "num_batches": 40, "batch_size": 128, "device": "cpu", "throughput_bps": 25651722.086006396, "sample_persec": 156.26049028999998, "result_path": "result/Batches/128/run 2", "data_path": "103.pt"}, {"total_cpu_time (seconds)": 21.798497325999772, "total_cpu_memory (MB)": 71466.756916, "execution_time (seconds/batch)": 0.5457085190158363, "num_batches": 40, "batch_size": 128, "device": "cpu", "throughput_bps": 38504951.394006416, "sample_persec": 234.55745244886947, "result_path": "result/Batches/128/run 2", "data_path": "27.pt"}, {"total_cpu_time (seconds)": 36.1076539849997, "total_cpu_memory (MB)": 71466.75698, "execution_time (seconds/batch)": 0.9039271875767576, "num_batches": 40, "batch_size": 128, "device": "cpu", "throughput_bps": 23245766.128940236, "sample_persec": 141.6043258341876, "result_path": "result/Batches/128/run 2", "data_path": "28.pt"}, {"total_cpu_time (seconds)": 22.859313807999957, "total_cpu_memory (MB)": 71466.75698, "execution_time (seconds/batch)": 0.5722652390815557, "num_batches": 40, "batch_size": 128, "device": "cpu", "throughput_bps": 36718078.54994567, "sample_persec": 223.67250578670607, "result_path": "result/Batches/128/run 2", "data_path": "29.pt"}, {"total_cpu_time (seconds)": 36.89004986699986, "total_cpu_memory (MB)": 71466.748268, "execution_time (seconds/batch)": 0.9235138632849564, "num_batches": 40, "batch_size": 128, "device": "cpu", "throughput_bps": 22752749.942765567, "sample_persec": 138.60105959287017, "result_path": "result/Batches/128/run 2", "data_path": "3.pt"}, {"total_cpu_time (seconds)": 21.124843815999917, "total_cpu_memory (MB)": 71466.756948, "execution_time (seconds/batch)": 0.5288441244764306, "num_batches": 40, "batch_size": 128, "device": "cpu", "throughput_bps": 39732841.92351177, "sample_persec": 242.03729241905322, "result_path": "result/Batches/128/run 2", "data_path": "30.pt"}, {"total_cpu_time (seconds)": 22.017993274999583, "total_cpu_memory (MB)": 71466.748276, "execution_time (seconds/batch)": 0.5512034303148732, "num_batches": 40, "batch_size": 128, "device": "cpu", "throughput_bps": 38121098.0272686, "sample_persec": 232.2191643961294, "result_path": "result/Batches/128/run 2", "data_path": "31.pt"}, {"total_cpu_time (seconds)": 23.873129116999593, "total_cpu_memory (MB)": 71466.756972, "execution_time (seconds/batch)": 0.5976453211374825, "num_batches": 40, "batch_size": 128, "device": "cpu", "throughput_bps": 35158779.391106926, "sample_persec": 214.1738510666845, "result_path": "result/Batches/128/run 2", "data_path": "32.pt"}, {"total_cpu_time (seconds)": 24.57502379600014, "total_cpu_memory (MB)": 71466.748284, "execution_time (seconds/batch)": 0.6152167114977543, "num_batches": 40, "batch_size": 128, "device": "cpu", "throughput_bps": 34154598.87109504, "sample_persec": 208.05676700228457, "result_path": "result/Batches/128/run 2", "data_path": "33.pt"}, {"total_cpu_time (seconds)": 22.751148915999988, "total_cpu_memory (MB)": 71466.756972, "execution_time (seconds/batch)": 0.5695574146778796, "num_batches": 40, "batch_size": 128, "device": "cpu", "throughput_bps": 36892645.86588496, "sample_persec": 224.73590317912377, "result_path": "result/Batches/128/run 2", "data_path": "34.pt"}, {"total_cpu_time (seconds)": 23.478499203000037, "total_cpu_memory (MB)": 71466.756972, "execution_time (seconds/batch)": 0.5877660664940357, "num_batches": 40, "batch_size": 128, "device": "cpu", "throughput_bps": 35749733.09591907, "sample_persec": 217.77371525291832, "result_path": "result/Batches/128/run 2", "data_path": "35.pt"}, {"total_cpu_time (seconds)": 22.632319042000066, "total_cpu_memory (MB)": 71466.75698, "execution_time (seconds/batch)": 0.5665826006993954, "num_batches": 40, "batch_size": 128, "device": "cpu", "throughput_bps": 37086348.88198469, "sample_persec": 225.91586794581318, "result_path": "result/Batches/128/run 2", "data_path": "104.pt"}, {"total_cpu_time (seconds)": 22.953402605000274, "total_cpu_memory (MB)": 71466.756972, "execution_time (seconds/batch)": 0.5746206793350352, "num_batches": 40, "batch_size": 128, "device": "cpu", "throughput_bps": 36567566.66731198, "sample_persec": 222.75564490321625, "result_path": "result/Batches/128/run 2", "data_path": "36.pt"}, {"total_cpu_time (seconds)": 34.15279142399969, "total_cpu_memory (MB)": 71466.7569, "execution_time (seconds/batch)": 0.8549887154844436, "num_batches": 40, "batch_size": 128, "device": "cpu", "throughput_bps": 24576324.364812415, "sample_persec": 149.70957824568967, "result_path": "result/Batches/128/run 2", "data_path": "37.pt"}, {"total_cpu_time (seconds)": 37.60334236999979, "total_cpu_memory (MB)": 71466.74826, "execution_time (seconds/batch)": 0.9413705893526252, "num_batches": 40, "batch_size": 128, "device": "cpu", "throughput_bps": 22321156.235027645, "sample_persec": 135.97195562273177, "result_path": "result/Batches/128/run 2", "data_path": "38.pt"}, {"total_cpu_time (seconds)": 25.69573725000007, "total_cpu_memory (MB)": 71466.756972, "execution_time (seconds/batch)": 0.6432729059260726, "num_batches": 40, "batch_size": 128, "device": "cpu", "throughput_bps": 32664954.18418079, "sample_persec": 198.98242071260228, "result_path": "result/Batches/128/run 2", "data_path": "39.pt"}, {"total_cpu_time (seconds)": 21.494376871000192, "total_cpu_memory (MB)": 71466.748276, "execution_time (seconds/batch)": 0.5380950986677145, "num_batches": 40, "batch_size": 128, "device": "cpu", "throughput_bps": 39049751.71122245, "sample_persec": 237.87616783152077, "result_path": "result/Batches/128/run 2", "data_path": "4.pt"}, {"total_cpu_time (seconds)": 22.56099223499999, "total_cpu_memory (MB)": 71466.75694, "execution_time (seconds/batch)": 0.564796989258752, "num_batches": 40, "batch_size": 128, "device": "cpu", "throughput_bps": 37203597.75213585, "sample_persec": 226.63010326593476, "result_path": "result/Batches/128/run 2", "data_path": "40.pt"}, {"total_cpu_time (seconds)": 23.74612249900019, "total_cpu_memory (MB)": 71466.756964, "execution_time (seconds/batch)": 0.5944658086978338, "num_batches": 40, "batch_size": 128, "device": "cpu", "throughput_bps": 35346826.83605882, "sample_persec": 215.31936425474427, "result_path": "result/Batches/128/run 2", "data_path": "41.pt"}, {"total_cpu_time (seconds)": 24.29753562399988, "total_cpu_memory (MB)": 71466.71346, "execution_time (seconds/batch)": 0.6082700097539575, "num_batches": 40, "batch_size": 128, "device": "cpu", "throughput_bps": 34544658.89005354, "sample_persec": 210.43286360900058, "result_path": "result/Batches/128/run 2", "data_path": "42.pt"}, {"total_cpu_time (seconds)": 23.366914783999793, "total_cpu_memory (MB)": 71466.756996, "execution_time (seconds/batch)": 0.5849726368769751, "num_batches": 40, "batch_size": 128, "device": "cpu", "throughput_bps": 35920449.39431776, "sample_persec": 218.8136537178226, "result_path": "result/Batches/128/run 2", "data_path": "43.pt"}, {"total_cpu_time (seconds)": 24.154616419000316, "total_cpu_memory (MB)": 71466.73086, "execution_time (seconds/batch)": 0.6046921380074399, "num_batches": 40, "batch_size": 128, "device": "cpu", "throughput_bps": 34749054.40186402, "sample_persec": 211.6779629743179, "result_path": "result/Batches/128/run 2", "data_path": "44.pt"}, {"total_cpu_time (seconds)": 25.259317944999687, "total_cpu_memory (MB)": 71466.756972, "execution_time (seconds/batch)": 0.6323474862037864, "num_batches": 40, "batch_size": 128, "device": "cpu", "throughput_bps": 33229324.79125617, "sample_persec": 202.4203508239289, "result_path": "result/Batches/128/run 2", "data_path": "105.pt"}, {"total_cpu_time (seconds)": 76.29701212399883, "total_cpu_memory (MB)": 71466.1594, "execution_time (seconds/batch)": 1.9100366813752885, "num_batches": 40, "batch_size": 128, "device": "cpu", "throughput_bps": 11001087.154446863, "sample_persec": 67.0144198004804, "result_path": "result/Batches/128/run 2", "data_path": "45.pt"}, {"total_cpu_time (seconds)": 23.06207101800019, "total_cpu_memory (MB)": 71466.756932, "execution_time (seconds/batch)": 0.5773411089974622, "num_batches": 40, "batch_size": 128, "device": "cpu", "throughput_bps": 36395260.397250466, "sample_persec": 221.70602093841657, "result_path": "result/Batches/128/run 2", "data_path": "46.pt"}, {"total_cpu_time (seconds)": 24.51844420999977, "total_cpu_memory (MB)": 71466.756964, "execution_time (seconds/batch)": 0.6138002853275906, "num_batches": 40, "batch_size": 128, "device": "cpu", "throughput_bps": 34233415.171492554, "sample_persec": 208.53688579125583, "result_path": "result/Batches/128/run 2", "data_path": "47.pt"}, {"total_cpu_time (seconds)": 22.192010194000474, "total_cpu_memory (MB)": 71466.756988, "execution_time (seconds/batch)": 0.5555598092767574, "num_batches": 40, "batch_size": 128, "device": "cpu", "throughput_bps": 37822174.407026686, "sample_persec": 230.39823591025026, "result_path": "result/Batches/128/run 2", "data_path": "48.pt"}, {"total_cpu_time (seconds)": 23.7533849399996, "total_cpu_memory (MB)": 71466.756964, "execution_time (seconds/batch)": 0.5946476182906216, "num_batches": 40, "batch_size": 128, "device": "cpu", "throughput_bps": 35336019.776557125, "sample_persec": 215.25353177727294, "result_path": "result/Batches/128/run 2", "data_path": "49.pt"}, {"total_cpu_time (seconds)": 21.236278568999936, "total_cpu_memory (MB)": 71466.748164, "execution_time (seconds/batch)": 0.531633807320945, "num_batches": 40, "batch_size": 128, "device": "cpu", "throughput_bps": 39524348.73524674, "sample_persec": 240.7672315743588, "result_path": "result/Batches/128/run 2", "data_path": "5.pt"}, {"total_cpu_time (seconds)": 23.032564392999678, "total_cpu_memory (MB)": 71466.756972, "execution_time (seconds/batch)": 0.5766024334644941, "num_batches": 40, "batch_size": 128, "device": "cpu", "throughput_bps": 36441885.74395584, "sample_persec": 221.99004473657314, "result_path": "result/Batches/128/run 2", "data_path": "50.pt"}, {"total_cpu_time (seconds)": 22.31216457400009, "total_cpu_memory (MB)": 71466.756876, "execution_time (seconds/batch)": 0.5585677812384141, "num_batches": 40, "batch_size": 128, "device": "cpu", "throughput_bps": 37618496.27884502, "sample_persec": 229.15750657191165, "result_path": "result/Batches/128/run 2", "data_path": "51.pt"}, {"total_cpu_time (seconds)": 22.482775282000006, "total_cpu_memory (MB)": 71466.756956, "execution_time (seconds/batch)": 0.5628388883426562, "num_batches": 40, "batch_size": 128, "device": "cpu", "throughput_bps": 37333028.03911376, "sample_persec": 227.41854312325634, "result_path": "result/Batches/128/run 2", "data_path": "52.pt"}, {"total_cpu_time (seconds)": 31.580058147000088, "total_cpu_memory (MB)": 71466.748244, "execution_time (seconds/batch)": 0.7905823279514984, "num_batches": 40, "batch_size": 128, "device": "cpu", "throughput_bps": 26578484.310983863, "sample_persec": 161.90597167996992, "result_path": "result/Batches/128/run 2", "data_path": "53.pt"}, {"total_cpu_time (seconds)": 22.66662866700037, "total_cpu_memory (MB)": 71466.756948, "execution_time (seconds/batch)": 0.567441515622149, "num_batches": 40, "batch_size": 128, "device": "cpu", "throughput_bps": 37030212.66775254, "sample_persec": 225.57390757646527, "result_path": "result/Batches/128/run 2", "data_path": "106.pt"}, {"total_cpu_time (seconds)": 23.52527884100019, "total_cpu_memory (MB)": 71466.756972, "execution_time (seconds/batch)": 0.588937158546455, "num_batches": 40, "batch_size": 128, "device": "cpu", "throughput_bps": 35678645.327560104, "sample_persec": 217.34067572831447, "result_path": "result/Batches/128/run 2", "data_path": "107.pt"}]