[{"total_cpu_time (seconds)": 7.06834941999998, "total_cpu_memory (MB)": 17864.672524, "execution_time (seconds/batch)": 2.8317643998747966, "num_batches": 3, "batch_size": 512, "device": "cpu", "throughput_bps": 29681113.30296976, "sample_persec": 180.80600208924074, "result_path": "result-partition-25MB/1GB/2", "data_path": "25MB/1.pt"}, {"total_cpu_time (seconds)": 6.448166311000017, "total_cpu_memory (MB)": 17864.672524, "execution_time (seconds/batch)": 2.5833029352363135, "num_batches": 3, "batch_size": 512, "device": "cpu", "throughput_bps": 32535835.75257748, "sample_persec": 198.19588055907334, "result_path": "result-partition-25MB/1GB/2", "data_path": "25MB/10.pt"}, {"total_cpu_time (seconds)": 6.548467714000013, "total_cpu_memory (MB)": 17864.672524, "execution_time (seconds/batch)": 2.6234862829170633, "num_batches": 3, "batch_size": 512, "device": "cpu", "throughput_bps": 32037491.694656245, "sample_persec": 195.16015895867596, "result_path": "result-partition-25MB/1GB/2", "data_path": "25MB/108.pt"}, {"total_cpu_time (seconds)": 6.728407567000012, "total_cpu_memory (MB)": 17864.672524, "execution_time (seconds/batch)": 2.6955748625226965, "num_batches": 3, "batch_size": 512, "device": "cpu", "throughput_bps": 31180703.295823343, "sample_persec": 189.94093138293948, "result_path": "result-partition-25MB/1GB/2", "data_path": "25MB/109.pt"}, {"total_cpu_time (seconds)": 6.7564393629999895, "total_cpu_memory (MB)": 17864.672524, "execution_time (seconds/batch)": 2.7068051282128285, "num_batches": 3, "batch_size": 512, "device": "cpu", "throughput_bps": 31051337.654105183, "sample_persec": 189.15288531984152, "result_path": "result-partition-25MB/1GB/2", "data_path": "25MB/11.pt"}, {"total_cpu_time (seconds)": 6.535782091999978, "total_cpu_memory (MB)": 17864.672524, "execution_time (seconds/batch)": 2.6184040931956094, "num_batches": 3, "batch_size": 512, "device": "cpu", "throughput_bps": 32099674.843321063, "sample_persec": 195.53895494225796, "result_path": "result-partition-25MB/1GB/2", "data_path": "25MB/110.pt"}, {"total_cpu_time (seconds)": 6.370705965000017, "total_cpu_memory (MB)": 17864.672524, "execution_time (seconds/batch)": 2.5522703083568143, "num_batches": 3, "batch_size": 512, "device": "cpu", "throughput_bps": 32931433.525985915, "sample_persec": 200.60571105010914, "result_path": "result-partition-25MB/1GB/2", "data_path": "25MB/111.pt"}, {"total_cpu_time (seconds)": 7.128981352999997, "total_cpu_memory (MB)": 17864.672524, "execution_time (seconds/batch)": 2.856055127336462, "num_batches": 3, "batch_size": 512, "device": "cpu", "throughput_bps": 29428675.65668608, "sample_persec": 179.2682483959922, "result_path": "result-partition-25MB/1GB/2", "data_path": "25MB/112.pt"}, {"total_cpu_time (seconds)": 6.726360109999993, "total_cpu_memory (MB)": 17864.672524, "execution_time (seconds/batch)": 2.694754598059465, "num_batches": 3, "batch_size": 512, "device": "cpu", "throughput_bps": 31190194.483952515, "sample_persec": 189.99874807475948, "result_path": "result-partition-25MB/1GB/2", "data_path": "25MB/113.pt"}, {"total_cpu_time (seconds)": 6.658005102000006, "total_cpu_memory (MB)": 17864.672524, "execution_time (seconds/batch)": 2.667369806122068, "num_batches": 3, "batch_size": 512, "device": "cpu", "throughput_bps": 31510411.419928018, "sample_persec": 191.94938730462974, "result_path": "result-partition-25MB/1GB/2", "data_path": "25MB/114.pt"}, {"total_cpu_time (seconds)": 7.229836898000007, "total_cpu_memory (MB)": 17864.672524, "execution_time (seconds/batch)": 2.8964604786979686, "num_batches": 3, "batch_size": 512, "device": "cpu", "throughput_bps": 29018148.39806913, "sample_persec": 176.76747318511897, "result_path": "result-partition-25MB/1GB/2", "data_path": "25MB/115.pt"}, {"total_cpu_time (seconds)": 7.244221005999966, "total_cpu_memory (MB)": 17864.672524, "execution_time (seconds/batch)": 2.902223126034415, "num_batches": 3, "batch_size": 512, "device": "cpu", "throughput_bps": 28960530.031626284, "sample_persec": 176.4164841107839, "result_path": "result-partition-25MB/1GB/2", "data_path": "25MB/116.pt"}, {"total_cpu_time (seconds)": 6.399288387000026, "total_cpu_memory (MB)": 17864.672524, "execution_time (seconds/batch)": 2.563721169126771, "num_batches": 3, "batch_size": 512, "device": "cpu", "throughput_bps": 32784345.27598344, "sample_persec": 199.7097056285541, "result_path": "result-partition-25MB/1GB/2", "data_path": "25MB/100.pt"}, {"total_cpu_time (seconds)": 7.017852884000002, "total_cpu_memory (MB)": 17864.672524, "execution_time (seconds/batch)": 2.8115341757496095, "num_batches": 3, "batch_size": 512, "device": "cpu", "throughput_bps": 29894681.9586821, "sample_persec": 182.1069807424592, "result_path": "result-partition-25MB/1GB/2", "data_path": "25MB/117.pt"}, {"total_cpu_time (seconds)": 7.098226949999973, "total_cpu_memory (MB)": 17864.672532, "execution_time (seconds/batch)": 2.84373411455398, "num_batches": 3, "batch_size": 512, "device": "cpu", "throughput_bps": 29556180.927689385, "sample_persec": 180.04496179148018, "result_path": "result-partition-25MB/1GB/2", "data_path": "25MB/118.pt"}, {"total_cpu_time (seconds)": 6.982646763000012, "total_cpu_memory (MB)": 17864.672524, "execution_time (seconds/batch)": 2.7974296890892068, "num_batches": 3, "batch_size": 512, "device": "cpu", "throughput_bps": 30045409.301195037, "sample_persec": 183.02515412521345, "result_path": "result-partition-25MB/1GB/2", "data_path": "25MB/119.pt"}, {"total_cpu_time (seconds)": 9.755969850999971, "total_cpu_memory (MB)": 17864.672524, "execution_time (seconds/batch)": 3.908494963780896, "num_batches": 3, "batch_size": 512, "device": "cpu", "throughput_bps": 21504420.698726963, "sample_persec": 130.9967147826935, "result_path": "result-partition-25MB/1GB/2", "data_path": "25MB/12.pt"}, {"total_cpu_time (seconds)": 6.586252763999968, "total_cpu_memory (MB)": 17864.672524, "execution_time (seconds/batch)": 2.6386239555305036, "num_batches": 3, "batch_size": 512, "device": "cpu", "throughput_bps": 31853693.97705688, "sample_persec": 194.04053348597026, "result_path": "result-partition-25MB/1GB/2", "data_path": "25MB/120.pt"}, {"total_cpu_time (seconds)": 6.575369660000025, "total_cpu_memory (MB)": 17864.672532, "execution_time (seconds/batch)": 2.6342639013458626, "num_batches": 3, "batch_size": 512, "device": "cpu", "throughput_bps": 31906416.041710302, "sample_persec": 194.36169616051598, "result_path": "result-partition-25MB/1GB/2", "data_path": "25MB/121.pt"}, {"total_cpu_time (seconds)": 7.181998733999993, "total_cpu_memory (MB)": 17864.672524, "execution_time (seconds/batch)": 2.877295267455396, "num_batches": 3, "batch_size": 512, "device": "cpu", "throughput_bps": 29211433.7206454, "sample_persec": 177.94489352245006, "result_path": "result-partition-25MB/1GB/2", "data_path": "25MB/122.pt"}, {"total_cpu_time (seconds)": 6.552351735000021, "total_cpu_memory (MB)": 17864.672524, "execution_time (seconds/batch)": 2.6250423226291164, "num_batches": 3, "batch_size": 512, "device": "cpu", "throughput_bps": 32018500.91156612, "sample_persec": 195.0444743638287, "result_path": "result-partition-25MB/1GB/2", "data_path": "25MB/123.pt"}, {"total_cpu_time (seconds)": 6.848462595000009, "total_cpu_memory (MB)": 17864.672524, "execution_time (seconds/batch)": 2.74367202553991, "num_batches": 3, "batch_size": 512, "device": "cpu", "throughput_bps": 30634098.83455744, "sample_persec": 186.61122584403898, "result_path": "result-partition-25MB/1GB/2", "data_path": "25MB/124.pt"}, {"total_cpu_time (seconds)": 6.742539514999986, "total_cpu_memory (MB)": 17864.672524, "execution_time (seconds/batch)": 2.7012364880125137, "num_batches": 3, "batch_size": 512, "device": "cpu", "throughput_bps": 31115350.460055918, "sample_persec": 189.54282687655893, "result_path": "result-partition-25MB/1GB/2", "data_path": "25MB/125.pt"}, {"total_cpu_time (seconds)": 6.869591633000014, "total_cpu_memory (MB)": 17864.672524, "execution_time (seconds/batch)": 2.752136867054779, "num_batches": 3, "batch_size": 512, "device": "cpu", "throughput_bps": 30539876.488754243, "sample_persec": 186.03725931258677, "result_path": "result-partition-25MB/1GB/2", "data_path": "25MB/101.pt"}, {"total_cpu_time (seconds)": 6.306371477000042, "total_cpu_memory (MB)": 17864.672524, "execution_time (seconds/batch)": 2.5264962411768557, "num_batches": 3, "batch_size": 512, "device": "cpu", "throughput_bps": 33267383.75072709, "sample_persec": 202.65219146398084, "result_path": "result-partition-25MB/1GB/2", "data_path": "25MB/126.pt"}, {"total_cpu_time (seconds)": 6.815489664999992, "total_cpu_memory (MB)": 17864.672524, "execution_time (seconds/batch)": 2.7304622132081344, "num_batches": 3, "batch_size": 512, "device": "cpu", "throughput_bps": 30782304.766359035, "sample_persec": 187.51403975608574, "result_path": "result-partition-25MB/1GB/2", "data_path": "25MB/127.pt"}, {"total_cpu_time (seconds)": 7.021695519999988, "total_cpu_memory (MB)": 17864.672524, "execution_time (seconds/batch)": 2.813073635555551, "num_batches": 3, "batch_size": 512, "device": "cpu", "throughput_bps": 29878322.03809378, "sample_persec": 182.00732235680908, "result_path": "result-partition-25MB/1GB/2", "data_path": "25MB/128.pt"}, {"total_cpu_time (seconds)": 6.797367836999995, "total_cpu_memory (MB)": 17864.672524, "execution_time (seconds/batch)": 2.723202138140843, "num_batches": 3, "batch_size": 512, "device": "cpu", "throughput_bps": 30864370.596220855, "sample_persec": 188.01395343701788, "result_path": "result-partition-25MB/1GB/2", "data_path": "25MB/129.pt"}, {"total_cpu_time (seconds)": 7.5932402189999975, "total_cpu_memory (MB)": 17864.672524, "execution_time (seconds/batch)": 3.0420492896150226, "num_batches": 3, "batch_size": 512, "device": "cpu", "throughput_bps": 27629374.805638567, "sample_persec": 168.30759506358777, "result_path": "result-partition-25MB/1GB/2", "data_path": "25MB/13.pt"}, {"total_cpu_time (seconds)": 7.712154382999974, "total_cpu_memory (MB)": 17864.672524, "execution_time (seconds/batch)": 3.089689392876359, "num_batches": 3, "batch_size": 512, "device": "cpu", "throughput_bps": 27203355.843401913, "sample_persec": 165.7124503131208, "result_path": "result-partition-25MB/1GB/2", "data_path": "25MB/130.pt"}, {"total_cpu_time (seconds)": 6.898671149000021, "total_cpu_memory (MB)": 17864.672524, "execution_time (seconds/batch)": 2.7637868765946876, "num_batches": 3, "batch_size": 512, "device": "cpu", "throughput_bps": 30411143.75054832, "sample_persec": 185.25306865587427, "result_path": "result-partition-25MB/1GB/2", "data_path": "25MB/131.pt"}, {"total_cpu_time (seconds)": 8.290679132000006, "total_cpu_memory (MB)": 17864.672524, "execution_time (seconds/batch)": 3.321461436294212, "num_batches": 3, "batch_size": 512, "device": "cpu", "throughput_bps": 25305101.869186636, "sample_persec": 154.1490123610297, "result_path": "result-partition-25MB/1GB/2", "data_path": "25MB/132.pt"}, {"total_cpu_time (seconds)": 9.39286890799998, "total_cpu_memory (MB)": 17864.672524, "execution_time (seconds/batch)": 3.7630272933458446, "num_batches": 3, "batch_size": 512, "device": "cpu", "throughput_bps": 22335718.943262875, "sample_persec": 136.06066607738106, "result_path": "result-partition-25MB/1GB/2", "data_path": "25MB/133.pt"}, {"total_cpu_time (seconds)": 7.099582873000003, "total_cpu_memory (MB)": 17864.672524, "execution_time (seconds/batch)": 2.8442773325320827, "num_batches": 3, "batch_size": 512, "device": "cpu", "throughput_bps": 29550536.102320094, "sample_persec": 180.01057567202787, "result_path": "result-partition-25MB/1GB/2", "data_path": "25MB/134.pt"}, {"total_cpu_time (seconds)": 7.360410107999977, "total_cpu_memory (MB)": 17864.672524, "execution_time (seconds/batch)": 2.9487714986666576, "num_batches": 3, "batch_size": 512, "device": "cpu", "throughput_bps": 28503368.279978547, "sample_persec": 173.63162938583423, "result_path": "result-partition-25MB/1GB/2", "data_path": "25MB/102.pt"}, {"total_cpu_time (seconds)": 25.73506327000008, "total_cpu_memory (MB)": 17864.672476, "execution_time (seconds/batch)": 10.31013489377155, "num_batches": 3, "batch_size": 512, "device": "cpu", "throughput_bps": 8152164.919857194, "sample_persec": 49.65987402447121, "result_path": "result-partition-25MB/1GB/2", "data_path": "25MB/103.pt"}, {"total_cpu_time (seconds)": 6.666978638000019, "total_cpu_memory (MB)": 17864.672524, "execution_time (seconds/batch)": 2.6709648377590063, "num_batches": 3, "batch_size": 512, "device": "cpu", "throughput_bps": 31467999.432938844, "sample_persec": 191.69102968408166, "result_path": "result-partition-25MB/1GB/2", "data_path": "25MB/104.pt"}, {"total_cpu_time (seconds)": 6.563257007000007, "total_cpu_memory (MB)": 17864.672524, "execution_time (seconds/batch)": 2.6294112578904567, "num_batches": 3, "batch_size": 512, "device": "cpu", "throughput_bps": 31965300.12099826, "sample_persec": 194.72039547391728, "result_path": "result-partition-25MB/1GB/2", "data_path": "25MB/105.pt"}, {"total_cpu_time (seconds)": 7.229746602999992, "total_cpu_memory (MB)": 17864.672524, "execution_time (seconds/batch)": 2.8964243041752704, "num_batches": 3, "batch_size": 512, "device": "cpu", "throughput_bps": 29018510.816540197, "sample_persec": 176.76968089997683, "result_path": "result-partition-25MB/1GB/2", "data_path": "25MB/106.pt"}, {"total_cpu_time (seconds)": 6.485318922999995, "total_cpu_memory (MB)": 17864.672524, "execution_time (seconds/batch)": 2.5981872367574317, "num_batches": 3, "batch_size": 512, "device": "cpu", "throughput_bps": 32349446.880085245, "sample_persec": 197.06047076075322, "result_path": "result-partition-25MB/1GB/2", "data_path": "25MB/107.pt"}]