[{"total_cpu_time (seconds)": 26.149332616999516, "total_cpu_memory (MB)": 71483.251516, "execution_time (seconds/batch)": 0.3273141575372519, "num_batches": 80, "batch_size": 64, "device": "cpu", "throughput_bps": 32098336.59212946, "sample_persec": 195.53080282729934, "result_path": "result/1GB/Batches/64/run 2", "data_path": "data/1.pt"}, {"total_cpu_time (seconds)": 31.42396241999926, "total_cpu_memory (MB)": 71483.251548, "execution_time (seconds/batch)": 0.39333729608448126, "num_batches": 80, "batch_size": 64, "device": "cpu", "throughput_bps": 26710510.55820413, "sample_persec": 162.71022513525907, "result_path": "result/1GB/Batches/64/run 2", "data_path": "data/10.pt"}, {"total_cpu_time (seconds)": 143.7735883159999, "total_cpu_memory (MB)": 71480.72242, "execution_time (seconds/batch)": 1.799630285981614, "num_batches": 80, "batch_size": 64, "device": "cpu", "throughput_bps": 5837999.105615928, "sample_persec": 35.56286004882997, "result_path": "result/1GB/Batches/64/run 2", "data_path": "data/100.pt"}, {"total_cpu_time (seconds)": 31.30861445999946, "total_cpu_memory (MB)": 71483.247228, "execution_time (seconds/batch)": 0.39189347260707325, "num_batches": 80, "batch_size": 64, "device": "cpu", "throughput_bps": 26808918.071809635, "sample_persec": 163.30968610995149, "result_path": "result/1GB/Batches/64/run 2", "data_path": "data/101.pt"}, {"total_cpu_time (seconds)": 31.243496885000344, "total_cpu_memory (MB)": 71483.247236, "execution_time (seconds/batch)": 0.3910783885468457, "num_batches": 80, "batch_size": 64, "device": "cpu", "throughput_bps": 26864793.11485017, "sample_persec": 163.65005552418478, "result_path": "result/1GB/Batches/64/run 2", "data_path": "data/102.pt"}, {"total_cpu_time (seconds)": 30.413539749999654, "total_cpu_memory (MB)": 71483.25162, "execution_time (seconds/batch)": 0.38068972110306626, "num_batches": 80, "batch_size": 64, "device": "cpu", "throughput_bps": 27597908.26386822, "sample_persec": 168.11591291342725, "result_path": "result/1GB/Batches/64/run 2", "data_path": "data/103.pt"}, {"total_cpu_time (seconds)": 34.37439197900032, "total_cpu_memory (MB)": 71483.247252, "execution_time (seconds/batch)": 0.4302681569833797, "num_batches": 80, "batch_size": 64, "device": "cpu", "throughput_bps": 24417888.773502316, "sample_persec": 148.74444915632503, "result_path": "result/1GB/Batches/64/run 2", "data_path": "data/104.pt"}, {"total_cpu_time (seconds)": 30.9609772120008, "total_cpu_memory (MB)": 71483.25162, "execution_time (seconds/batch)": 0.3875420578071682, "num_batches": 80, "batch_size": 64, "device": "cpu", "throughput_bps": 27109935.007951207, "sample_persec": 165.1433662765059, "result_path": "result/1GB/Batches/64/run 2", "data_path": "data/105.pt"}, {"total_cpu_time (seconds)": 26.26510330300022, "total_cpu_memory (MB)": 71483.242852, "execution_time (seconds/batch)": 0.3287632723238831, "num_batches": 80, "batch_size": 64, "device": "cpu", "throughput_bps": 31956854.321761698, "sample_persec": 194.6689468918232, "result_path": "result/1GB/Batches/64/run 2", "data_path": "data/106.pt"}, {"total_cpu_time (seconds)": 36.7627131860004, "total_cpu_memory (MB)": 71483.229516, "execution_time (seconds/batch)": 0.46016304398670554, "num_batches": 80, "batch_size": 64, "device": "cpu", "throughput_bps": 22831559.67714681, "sample_persec": 139.0811383841789, "result_path": "result/1GB/Batches/64/run 2", "data_path": "data/107.pt"}]