[{"total_cpu_time (seconds)": 26.09854515400001, "total_cpu_memory (MB)": 71461.283356, "execution_time (seconds/batch)": 2.61342756089341, "num_batches": 10, "batch_size": 512, "device": "cpu", "throughput_bps": 32160799.578951105, "sample_persec": 195.911303478016, "result_path": "result/2GB/run 3", "data_path": "1.pt"}, {"total_cpu_time (seconds)": 21.991839822999978, "total_cpu_memory (MB)": 71461.283356, "execution_time (seconds/batch)": 2.2021947954969665, "num_batches": 10, "batch_size": 512, "device": "cpu", "throughput_bps": 38166432.94765056, "sample_persec": 232.49532741015204, "result_path": "result/2GB/run 3", "data_path": "2.pt"}, {"total_cpu_time (seconds)": 28.133460664999895, "total_cpu_memory (MB)": 71461.283356, "execution_time (seconds/batch)": 2.8171977039859075, "num_batches": 10, "batch_size": 512, "device": "cpu", "throughput_bps": 29834583.45187564, "sample_persec": 181.74088360060694, "result_path": "result/2GB/run 3", "data_path": "11.pt"}, {"total_cpu_time (seconds)": 21.76271017700003, "total_cpu_memory (MB)": 71461.283356, "execution_time (seconds/batch)": 2.1792504616905957, "num_batches": 10, "batch_size": 512, "device": "cpu", "throughput_bps": 38568269.90634048, "sample_persec": 234.94316463414035, "result_path": "result/2GB/run 3", "data_path": "12.pt"}, {"total_cpu_time (seconds)": 23.005234359000045, "total_cpu_memory (MB)": 71461.283356, "execution_time (seconds/batch)": 2.3036729888143994, "num_batches": 10, "batch_size": 512, "device": "cpu", "throughput_bps": 36485178.41208741, "sample_persec": 222.2537671301621, "result_path": "result/2GB/run 3", "data_path": "13.pt"}, {"total_cpu_time (seconds)": 22.928937594000033, "total_cpu_memory (MB)": 71461.283364, "execution_time (seconds/batch)": 2.2960328668351293, "num_batches": 10, "batch_size": 512, "device": "cpu", "throughput_bps": 36606583.99714247, "sample_persec": 222.99332356933766, "result_path": "result/2GB/run 3", "data_path": "14.pt"}, {"total_cpu_time (seconds)": 25.81598763999982, "total_cpu_memory (MB)": 71461.283348, "execution_time (seconds/batch)": 2.5851331256952683, "num_batches": 10, "batch_size": 512, "device": "cpu", "throughput_bps": 32512801.43547535, "sample_persec": 198.05556429992293, "result_path": "result/2GB/run 3", "data_path": "15.pt"}, {"total_cpu_time (seconds)": 21.00104679500019, "total_cpu_memory (MB)": 71461.283364, "execution_time (seconds/batch)": 2.102979847259945, "num_batches": 10, "batch_size": 512, "device": "cpu", "throughput_bps": 39967059.17534681, "sample_persec": 243.46405443071887, "result_path": "result/2GB/run 3", "data_path": "16.pt"}, {"total_cpu_time (seconds)": 21.740384448999894, "total_cpu_memory (MB)": 71461.283356, "execution_time (seconds/batch)": 2.177014832366115, "num_batches": 10, "batch_size": 512, "device": "cpu", "throughput_bps": 38607876.59799696, "sample_persec": 235.1844334673304, "result_path": "result/2GB/run 3", "data_path": "17.pt"}, {"total_cpu_time (seconds)": 22.660736496999792, "total_cpu_memory (MB)": 71461.283356, "execution_time (seconds/batch)": 2.2691760388155475, "num_batches": 10, "batch_size": 512, "device": "cpu", "throughput_bps": 37039841.14157663, "sample_persec": 225.6325605602865, "result_path": "result/2GB/run 3", "data_path": "18.pt"}, {"total_cpu_time (seconds)": 20.30030633899997, "total_cpu_memory (MB)": 71461.28334, "execution_time (seconds/batch)": 2.0328098661388587, "num_batches": 10, "batch_size": 512, "device": "cpu", "throughput_bps": 41346670.63557958, "sample_persec": 251.86812034344283, "result_path": "result/2GB/run 3", "data_path": "19.pt"}, {"total_cpu_time (seconds)": 20.54291528899999, "total_cpu_memory (MB)": 71461.283356, "execution_time (seconds/batch)": 2.0571039757418332, "num_batches": 10, "batch_size": 512, "device": "cpu", "throughput_bps": 40858372.25106227, "sample_persec": 248.89359314730916, "result_path": "result/2GB/run 3", "data_path": "20.pt"}, {"total_cpu_time (seconds)": 22.947312514999865, "total_cpu_memory (MB)": 71461.283356, "execution_time (seconds/batch)": 2.2978728745706887, "num_batches": 10, "batch_size": 512, "device": "cpu", "throughput_bps": 36577271.49753793, "sample_persec": 222.81476302106438, "result_path": "result/2GB/run 3", "data_path": "3.pt"}, {"total_cpu_time (seconds)": 25.129230736999943, "total_cpu_memory (MB)": 71461.283356, "execution_time (seconds/batch)": 2.51636341430549, "num_batches": 10, "batch_size": 512, "device": "cpu", "throughput_bps": 33401343.98798576, "sample_persec": 203.46822604767152, "result_path": "result/2GB/run 3", "data_path": "4.pt"}, {"total_cpu_time (seconds)": 24.578770639000105, "total_cpu_memory (MB)": 71461.283356, "execution_time (seconds/batch)": 2.4612420432560245, "num_batches": 10, "batch_size": 512, "device": "cpu", "throughput_bps": 34149392.26733212, "sample_persec": 208.0250503614286, "result_path": "result/2GB/run 3", "data_path": "5.pt"}, {"total_cpu_time (seconds)": 19.533771521000013, "total_cpu_memory (MB)": 71461.283364, "execution_time (seconds/batch)": 1.9560514411797392, "num_batches": 10, "batch_size": 512, "device": "cpu", "throughput_bps": 42969176.694712885, "sample_persec": 261.7518073508339, "result_path": "result/2GB/run 3", "data_path": "6.pt"}, {"total_cpu_time (seconds)": 20.72930875400015, "total_cpu_memory (MB)": 71461.283356, "execution_time (seconds/batch)": 2.075768840611789, "num_batches": 10, "batch_size": 512, "device": "cpu", "throughput_bps": 40490982.596707664, "sample_persec": 246.65559574017828, "result_path": "result/2GB/run 3", "data_path": "7.pt"}, {"total_cpu_time (seconds)": 24.43736392099999, "total_cpu_memory (MB)": 71461.283356, "execution_time (seconds/batch)": 2.4470820120383325, "num_batches": 10, "batch_size": 512, "device": "cpu", "throughput_bps": 34346997.602254204, "sample_persec": 209.22878656343934, "result_path": "result/2GB/run 3", "data_path": "8.pt"}, {"total_cpu_time (seconds)": 22.517379968000117, "total_cpu_memory (MB)": 71461.283356, "execution_time (seconds/batch)": 2.254820759557219, "num_batches": 10, "batch_size": 512, "device": "cpu", "throughput_bps": 37275654.68064298, "sample_persec": 227.0690465438778, "result_path": "result/2GB/run 3", "data_path": "9.pt"}, {"total_cpu_time (seconds)": 22.75244107099995, "total_cpu_memory (MB)": 71461.283356, "execution_time (seconds/batch)": 2.2783590511151917, "num_batches": 10, "batch_size": 512, "device": "cpu", "throughput_bps": 36890550.66138937, "sample_persec": 224.72313999384366, "result_path": "result/2GB/run 3", "data_path": "10.pt"}]